main_module_my_test/__init__.py
main_module_my_test/test_inside.py
main_module_my_test/test_inside_2.py
main_module_my_test/extras/__init__.py
main_module_my_test/extras/test_extra.py
main_module_my_test-0.0.5.dist-info/METADATA
main_module_my_test-0.0.5.dist-info/WHEEL
main_module_my_test-0.0.5.dist-info/top_level.txt
main_module_my_test-0.0.5.dist-info/RECORD
