Metadata-Version: 2.1
Name: main-module-my-test
Version: 0.0.5
Summary: Mi primer paquete de Python
Author: Hernan Hernandez
Author-email: <test@email.com>
License: UNKNOWN
Keywords: python,primer paquete
Platform: UNKNOWN
Classifier: Development Status :: 3 - Alpha
Classifier: Intended Audience :: Education
Classifier: Programming Language :: Python :: 2
Classifier: Programming Language :: Python :: 3
Classifier: Operating System :: MacOS :: MacOS X
Classifier: Operating System :: Microsoft :: Windows
